pygrid/__init__.py
pygrid/central_data/__init__.py
pygrid/central_data/base_client.py
pygrid/central_data/base_model.py
pygrid/central_data/client.py
pygrid/central_data/enums.py
pygrid/central_data/exceptions.py
pygrid/central_data/get_available_games.py
pygrid/central_data/get_available_players.py
pygrid/central_data/get_available_teams.py
pygrid/central_data/get_available_tournaments.py
pygrid/central_data/get_games.py
pygrid/central_data/get_lol_teams_by_team_code.py
pygrid/central_data/get_series.py
pygrid/central_data/get_series_ids_by_team.py
pygrid/central_data/input_types.py
pygrid/client/__init__.py
pygrid/client/client.py
pygrid/client/extended_clients.py
pygrid/pipeline/__init__.py
pygrid/pipeline/champions.py
pygrid/pipeline/constants.py
pygrid/pipeline/parsers.py
pygrid/pipeline/streams.py
pygrid/pipeline/transformations.py
pygrid/series_state/__init__.py
pygrid/series_state/base_client.py
pygrid/series_state/base_model.py
pygrid/series_state/client.py
pygrid/series_state/enums.py
pygrid/series_state/exceptions.py
pygrid/series_state/input_types.py
pygrid/series_state/series_draft_state.py
pygrid/series_state/series_draft_summary.py
pygrid/series_state/series_games.py
pygrid/series_state/series_state.py
pygrid/series_state/series_state_legacy.py
grid_lol_client-0.2.7.dist-info/LICENSE
grid_lol_client-0.2.7.dist-info/METADATA
grid_lol_client-0.2.7.dist-info/WHEEL
grid_lol_client-0.2.7.dist-info/RECORD
