Metadata-Version: 2.3
Name: grid-lol-client
Version: 0.2.7
Summary: Python client for the GRID Esports API and ETL helper functions for game data processing
License: MIT
Author: Allan Cao
Author-email: allan@allancao.ca
Requires-Python: >=3.10, <4
Classifier: License :: OSI Approved :: MIT License
Classifier: Programming Language :: Python :: 3
Classifier: Programming Language :: Python :: 3.10
Classifier: Programming Language :: Python :: 3.11
Classifier: Programming Language :: Python :: 3.12
Classifier: Programming Language :: Python :: 3.13
Requires-Dist: httpx (>=0.28.1,<0.29.0)
Requires-Dist: orjson (>=3.10.18,<4.0.0)
Requires-Dist: pendulum (>=3.1.0,<4.0.0)
Requires-Dist: pydantic (>=2.11.7,<3.0.0)
Requires-Dist: tqdm (>=4.67.1,<5.0.0)
